{"path":"D:\\ADelplanque\\Object Detection Model\\M2\\data\\train\\E1V3_DSC06628.JPG","outputs":{"object":[{"name":"warthog","bndbox":{"xmin":4215,"ymin":1274,"xmax":4246,"ymax":1318}},{"name":"warthog","bndbox":{"xmin":4160,"ymin":1416,"xmax":4181,"ymax":1457}},{"name":"warthog","bndbox":{"xmin":4098,"ymin":1395,"xmax":4120,"ymax":1423}},{"name":"warthog","bndbox":{"xmin":3928,"ymin":1278,"xmax":3960,"ymax":1311}},{"name":"warthog","bndbox":{"xmin":3953,"ymin":1077,"xmax":3972,"ymax":1107}}]},"time_labeled":1585657484801,"labeled":true,"size":{"width":6000,"height":4000,"depth":3}}