{"path":"D:\\ADelplanque\\Object Detection Model\\M2\\data\\train\\L_07_05_16_DSC00414.JPG","outputs":{"object":[{"name":"hippopotamus","bndbox":{"xmin":5314,"ymin":1276,"xmax":5381,"ymax":1338}},{"name":"buffalo","bndbox":{"xmin":5833,"ymin":992,"xmax":5903,"ymax":1033}},{"name":"buffalo","bndbox":{"xmin":5802,"ymin":961,"xmax":5881,"ymax":1010}},{"name":"buffalo","bndbox":{"xmin":5693,"ymin":987,"xmax":5773,"ymax":1044}},{"name":"buffalo","bndbox":{"xmin":5327,"ymin":743,"xmax":5398,"ymax":804}},{"name":"buffalo","bndbox":{"xmin":5464,"ymin":633,"xmax":5516,"ymax":704}},{"name":"buffalo","bndbox":{"xmin":5735,"ymin":744,"xmax":5780,"ymax":795}},{"name":"buffalo","bndbox":{"xmin":5742,"ymin":783,"xmax":5790,"ymax":837}},{"name":"buffalo","bndbox":{"xmin":5653,"ymin":819,"xmax":5702,"ymax":879}},{"name":"buffalo","bndbox":{"xmin":5577,"ymin":810,"xmax":5621,"ymax":859}},{"name":"buffalo","bndbox":{"xmin":5566,"ymin":777,"xmax":5619,"ymax":816}},{"name":"buffalo","bndbox":{"xmin":5596,"ymin":757,"xmax":5635,"ymax":792}},{"name":"buffalo","bndbox":{"xmin":5540,"ymin":734,"xmax":5598,"ymax":783}},{"name":"buffalo","bndbox":{"xmin":5560,"ymin":705,"xmax":5642,"ymax":750}},{"name":"buffalo","bndbox":{"xmin":5754,"ymin":646,"xmax":5805,"ymax":705}},{"name":"buffalo","bndbox":{"xmin":5875,"ymin":691,"xmax":5940,"ymax":742}},{"name":"buffalo","bndbox":{"xmin":5939,"ymin":660,"xmax":5977,"ymax":716}},{"name":"buffalo","bndbox":{"xmin":5962,"ymin":691,"xmax":5999,"ymax":743}},{"name":"buffalo","bndbox":{"xmin":5867,"ymin":655,"xmax":5913,"ymax":696}},{"name":"buffalo","bndbox":{"xmin":5821,"ymin":630,"xmax":5892,"ymax":678}},{"name":"buffalo","bndbox":{"xmin":5788,"ymin":598,"xmax":5878,"ymax":643}},{"name":"buffalo","bndbox":{"xmin":5924,"ymin":621,"xmax":5994,"ymax":665}},{"name":"buffalo","bndbox":{"xmin":5885,"ymin":594,"xmax":5939,"ymax":635}},{"name":"buffalo","bndbox":{"xmin":5834,"ymin":557,"xmax":5921,"ymax":595}},{"name":"buffalo","bndbox":{"xmin":5777,"ymin":489,"xmax":5822,"ymax":554}},{"name":"buffalo","bndbox":{"xmin":5836,"ymin":497,"xmax":5876,"ymax":560}},{"name":"buffalo","bndbox":{"xmin":5841,"ymin":409,"xmax":5895,"ymax":461}},{"name":"buffalo","bndbox":{"xmin":5871,"ymin":448,"xmax":5940,"ymax":510}},{"name":"buffalo","bndbox":{"xmin":5881,"ymin":493,"xmax":5953,"ymax":533}},{"name":"buffalo","bndbox":{"xmin":5946,"ymin":511,"xmax":6003,"ymax":559}},{"name":"buffalo","bndbox":{"xmin":5954,"ymin":545,"xmax":6007,"ymax":612}},{"name":"buffalo","bndbox":{"xmin":5916,"ymin":528,"xmax":5963,"ymax":575}},{"name":"buffalo","bndbox":{"xmin":5905,"ymin":242,"xmax":5965,"ymax":306}},{"name":"buffalo","bndbox":{"xmin":5757,"ymin":238,"xmax":5821,"ymax":310}},{"name":"buffalo","bndbox":{"xmin":5746,"ymin":299,"xmax":5791,"ymax":346}},{"name":"buffalo","bndbox":{"xmin":5785,"ymin":300,"xmax":5825,"ymax":346}},{"name":"buffalo","bndbox":{"xmin":5815,"ymin":266,"xmax":5846,"ymax":330}}]},"time_labeled":1585662114179,"labeled":true,"size":{"width":6000,"height":4000,"depth":3}}