{"path":"D:\\ADelplanque\\Object Detection Model\\M2\\data\\train\\L_11_05_16_DSC01347.JPG","outputs":{"object":[{"name":"buffalo","bndbox":{"xmin":2547,"ymin":3225,"xmax":2601,"ymax":3317}},{"name":"buffalo","bndbox":{"xmin":2441,"ymin":3534,"xmax":2555,"ymax":3626}},{"name":"buffalo","bndbox":{"xmin":2323,"ymin":3715,"xmax":2398,"ymax":3823}},{"name":"buffalo","bndbox":{"xmin":1270,"ymin":3845,"xmax":1333,"ymax":3921}}]},"time_labeled":1585824050634,"labeled":true,"size":{"width":6000,"height":4000,"depth":3}}