{"path":"D:\\ADelplanque\\Object Detection Model\\M2\\data\\train\\S_08_05_16_DSC00795.JPG","outputs":{"object":[{"name":"topi","bndbox":{"xmin":1288,"ymin":1781,"xmax":1337,"ymax":1808}},{"name":"topi","bndbox":{"xmin":1223,"ymin":1820,"xmax":1272,"ymax":1857}},{"name":"topi","bndbox":{"xmin":953,"ymin":1991,"xmax":1008,"ymax":2034}},{"name":"topi","bndbox":{"xmin":425,"ymin":1839,"xmax":472,"ymax":1903}},{"name":"topi","bndbox":{"xmin":706,"ymin":1530,"xmax":762,"ymax":1585}},{"name":"topi","bndbox":{"xmin":661,"ymin":1571,"xmax":701,"ymax":1604}},{"name":"topi","bndbox":{"xmin":84,"ymin":1447,"xmax":149,"ymax":1504}},{"name":"topi","bndbox":{"xmin":251,"ymin":1024,"xmax":304,"ymax":1074}}]},"time_labeled":1585833888032,"labeled":true,"size":{"width":6000,"height":4000,"depth":3}}