{"path":"D:\\ADelplanque\\Object Detection Model\\M2\\data\\train\\S_10_05_16_DSC00810.JPG","outputs":{"object":[{"name":"buffalo","bndbox":{"xmin":2888,"ymin":396,"xmax":2960,"ymax":465}},{"name":"buffalo","bndbox":{"xmin":3141,"ymin":734,"xmax":3182,"ymax":836}},{"name":"buffalo","bndbox":{"xmin":3161,"ymin":730,"xmax":3202,"ymax":777}},{"name":"buffalo","bndbox":{"xmin":2474,"ymin":1127,"xmax":2544,"ymax":1226}},{"name":"buffalo","bndbox":{"xmin":2114,"ymin":955,"xmax":2174,"ymax":1014}},{"name":"buffalo","bndbox":{"xmin":1833,"ymin":1207,"xmax":1943,"ymax":1268}},{"name":"buffalo","bndbox":{"xmin":2078,"ymin":1518,"xmax":2130,"ymax":1587}},{"name":"buffalo","bndbox":{"xmin":1026,"ymin":2262,"xmax":1083,"ymax":2350}},{"name":"buffalo","bndbox":{"xmin":1259,"ymin":2537,"xmax":1323,"ymax":2635}},{"name":"buffalo","bndbox":{"xmin":1245,"ymin":2724,"xmax":1309,"ymax":2820}},{"name":"buffalo","bndbox":{"xmin":1216,"ymin":3075,"xmax":1264,"ymax":3185}},{"name":"buffalo","bndbox":{"xmin":1260,"ymin":3123,"xmax":1301,"ymax":3199}},{"name":"buffalo","bndbox":{"xmin":1771,"ymin":3074,"xmax":1832,"ymax":3114}},{"name":"buffalo","bndbox":{"xmin":1771,"ymin":3245,"xmax":1830,"ymax":3356}},{"name":"buffalo","bndbox":{"xmin":1606,"ymin":3444,"xmax":1647,"ymax":3532}},{"name":"buffalo","bndbox":{"xmin":1259,"ymin":3468,"xmax":1319,"ymax":3545}},{"name":"buffalo","bndbox":{"xmin":1246,"ymin":3672,"xmax":1307,"ymax":3780}},{"name":"buffalo","bndbox":{"xmin":1655,"ymin":3707,"xmax":1701,"ymax":3829}},{"name":"buffalo","bndbox":{"xmin":2505,"ymin":3876,"xmax":2543,"ymax":3984}},{"name":"buffalo","bndbox":{"xmin":2881,"ymin":3665,"xmax":2942,"ymax":3773}},{"name":"buffalo","bndbox":{"xmin":2971,"ymin":3536,"xmax":3027,"ymax":3588}},{"name":"buffalo","bndbox":{"xmin":2567,"ymin":3086,"xmax":2609,"ymax":3154}},{"name":"buffalo","bndbox":{"xmin":2613,"ymin":2836,"xmax":2672,"ymax":2940}},{"name":"buffalo","bndbox":{"xmin":2182,"ymin":2734,"xmax":2236,"ymax":2826}},{"name":"buffalo","bndbox":{"xmin":2003,"ymin":2620,"xmax":2069,"ymax":2672}},{"name":"buffalo","bndbox":{"xmin":2066,"ymin":2642,"xmax":2099,"ymax":2708}},{"name":"buffalo","bndbox":{"xmin":2166,"ymin":2579,"xmax":2221,"ymax":2669}},{"name":"buffalo","bndbox":{"xmin":2317,"ymin":2413,"xmax":2415,"ymax":2472}},{"name":"buffalo","bndbox":{"xmin":2373,"ymin":2269,"xmax":2473,"ymax":2312}},{"name":"buffalo","bndbox":{"xmin":2718,"ymin":2598,"xmax":2767,"ymax":2675}},{"name":"buffalo","bndbox":{"xmin":3011,"ymin":2725,"xmax":3112,"ymax":2787}},{"name":"buffalo","bndbox":{"xmin":2962,"ymin":2846,"xmax":3046,"ymax":2888}},{"name":"buffalo","bndbox":{"xmin":2999,"ymin":3079,"xmax":3075,"ymax":3153}},{"name":"buffalo","bndbox":{"xmin":4934,"ymin":3533,"xmax":4987,"ymax":3653}},{"name":"buffalo","bndbox":{"xmin":4683,"ymin":1562,"xmax":4738,"ymax":1661}},{"name":"buffalo","bndbox":{"xmin":4568,"ymin":1523,"xmax":4663,"ymax":1593}}]},"time_labeled":1585906656814,"labeled":true,"size":{"width":6000,"height":4000,"depth":3}}